{
  "navigation": [
    {
      "type": "regular",
      "name": "Homepage",
      "action": "/",
      "icon": "FaHome",
      "icon_library": "fa6"
    },
    {
      "type": "regular",
      "name": "New Arrivals",
      "action": "new_arrivals",
      "icon": "FaAward",
      "icon_library": "fa"
    },
    {
      "type": "regular",
      "name": "On Sale",
      "action": "sales",
      "icon": "FaPercent",
      "icon_library": "fa"
    },
    {
      "type": "regular",
      "name": "Most Wanted",
      "action": "most_wanted",
      "icon": "FaHeart",
      "icon_library": "fa"
    },
    {
      "type": "dropdown",
      "name": "Accessories",
      "action": "none",
      "dropdown_links": [
        { "name": "Hat", "action": "etalase/jeans" },
        { "name": "Carrier", "action": "etalase/pants" },
        { "name": "Backpack", "action": "etalase/pants" },
        { "name": "Casual Bag", "action": "etalase/pants" }
      ],
      "icon": "FaRedhat",
      "icon_library": "fa"
    },
    {
      "type": "dropdown",
      "name": "Tops & Outers",
      "action": "none",
      "dropdown_links": [
        { "name": "T-Shirt", "action": "etalase/t_shirts" },
        { "name": "Shirts", "action": "etalase/shirts" },
        { "name": "Blazzers", "action": "etalase/blazzers" },
        { "name": "Jackets", "action": "etalase/jackets" }
      ],
      "icon": "IoShirtSharp",
      "icon_library": "io5"
    },
    {
      "type": "dropdown",
      "name": "Bottoms",
      "action": "none",
      "dropdown_links": [
        { "name": "Jeans", "action": "etalase/jeans" },
        { "name": "Pants", "action": "etalase/pants" },
        { "name": "Shorts", "action": "etalase/shorts" },
        { "name": "Shoes", "action": "etalase/shoes" }
      ],
      "icon": "GiArmoredPants",
      "icon_library": "gi"
    },
    {
      "type": "dropdown",
      "name": "Bottoms",
      "action": "none",
      "dropdown_links": [
        { "name": "Everyday", "action": "categories/everyday" },
        { "name": "Casual", "action": "categories/casual" },
        { "name": "Simple", "action": "categories/simple" },
        { "name": "Modest", "action": "categories/modest" },
        { "name": "Hiking Wear", "action": "categories/adventure" }
      ],
      "icon": "BiCategory",
      "icon_library": "bi"
    }
  ]
}
